async_download/__init__.py
async_download/cli.py
async_download-1.4.0.dist-info/AUTHORS.rst
async_download-1.4.0.dist-info/LICENSE
async_download-1.4.0.dist-info/METADATA
async_download-1.4.0.dist-info/WHEEL
async_download-1.4.0.dist-info/entry_points.txt
async_download-1.4.0.dist-info/top_level.txt
async_download-1.4.0.dist-info/RECORD
