Metadata-Version: 2.1
Name: async_download
Version: 1.4.0
Summary: Uses coroutines to download files
Home-page: https://github.com/danwald/async_download
Author: danny crasto
Author-email: danwald79@gmail.com
License: MIT license
Keywords: async_download
Classifier: Development Status :: 2 - Pre-Alpha
Classifier: Intended Audience :: Developers
Classifier: License :: OSI Approved :: MIT License
Classifier: Natural Language :: English
Classifier: Programming Language :: Python :: 3
Classifier: Programming Language :: Python :: 3.10
Classifier: Programming Language :: Python :: 3.11
Requires-Python: >=3.10
License-File: LICENSE
License-File: AUTHORS.rst
Requires-Dist: Click >=8.1.7
Requires-Dist: aiohttp >=3.8.6
Requires-Dist: more-itertools >=10.1.0
Requires-Dist: pip >=22
Requires-Dist: tqdm >=4.66.1
Provides-Extra: dev
Requires-Dist: Sphinx >=1.8.5 ; extra == 'dev'
Requires-Dist: black >=23.9.1 ; extra == 'dev'
Requires-Dist: bump2version >=1.0.1 ; extra == 'dev'
Requires-Dist: coverage >=7.3.2 ; extra == 'dev'
Requires-Dist: flake8 >=6.1.0 ; extra == 'dev'
Requires-Dist: pip >=22.3.1 ; extra == 'dev'
Requires-Dist: tox >=4.11.3 ; extra == 'dev'
Requires-Dist: twine >=4.0.2 ; extra == 'dev'
Requires-Dist: watchdog >=3.0.0 ; extra == 'dev'
Requires-Dist: wheel >=0.33.6 ; extra == 'dev'
Provides-Extra: testing
Requires-Dist: isort >=5.12.0 ; extra == 'testing'
Requires-Dist: pre-commit >=3.4.0 ; extra == 'testing'
Requires-Dist: pytest >=7.4.2 ; extra == 'testing'
